README.rst
setup.py
django_gevent_websocket.egg-info/PKG-INFO
django_gevent_websocket.egg-info/SOURCES.txt
django_gevent_websocket.egg-info/dependency_links.txt
django_gevent_websocket.egg-info/requires.txt
django_gevent_websocket.egg-info/top_level.txt
django_websocket/__init__.py
django_websocket/conf.py
django_websocket/decorators.py
django_websocket/models.py
django_websocket/wsgi.py