Metadata-Version: 1.1
Name: django-gevent-websocket
Version: 0.1.0
Summary: Easy WebSocket server for django using gevent-websocket
Home-page: http://bitbucket.org/schinckel/django-gevent-websocket/
Author: Matthew Schinckel
Author-email: matt@schinckel.net
License: UNKNOWN
Platform: UNKNOWN
Classifier: Programming Language :: Python
Classifier: License :: OSI Approved :: BSD License
Classifier: Operating System :: OS Independent
Classifier: Framework :: Django
